LICENSE.txt
MANIFEST.in
README.txt
setup.py
trizio2sce.py
trizio2sce.egg-info/PKG-INFO
trizio2sce.egg-info/SOURCES.txt
trizio2sce.egg-info/dependency_links.txt
trizio2sce.egg-info/top_level.txt