Metadata-Version: 1.2
Name: trizio2sce
Version: 1.0.5
Summary: Convierte mapas de aventuras de texto generados por Trizbort.io en código fuente para el DAAD.
Home-page: http://www.zonafi.rockersuke.com/trizio2sce/index.html
Author: Pedro Fernández
Author-email: rockersuke@gmail.com
License: MIT
Platform: UNKNOWN
Requires-Python: >=3.5
